pbatch/__init__.py
pbatch/main.py
pbatch/version.py
pbatch-0.2.0.dist-info/LICENSE
pbatch-0.2.0.dist-info/METADATA
pbatch-0.2.0.dist-info/WHEEL
pbatch-0.2.0.dist-info/top_level.txt
pbatch-0.2.0.dist-info/RECORD
