Metadata-Version: 2.1
Name: pbatch
Version: 0.2.0
Summary: Parallel batch processing on top of regular python functions
Home-page: https://github.com/nayaverdier/pbatch
Author: Naya Verdier
License: MIT
Platform: UNKNOWN
Classifier: Programming Language :: Python :: 3
Requires-Python: >=3.7
Provides-Extra: dev
Requires-Dist: black (==20.8b1) ; extra == 'dev'
Requires-Dist: coverage (==5.2.1) ; extra == 'dev'
Requires-Dist: flake8 (==3.8.3) ; extra == 'dev'
Requires-Dist: flake8-bugbear (==20.1.4) ; extra == 'dev'
Requires-Dist: isort (==5.5.1) ; extra == 'dev'
Requires-Dist: mypy (==0.782) ; extra == 'dev'
Requires-Dist: pytest (==6.0.1) ; extra == 'dev'
Requires-Dist: pytest-cov (==2.10.1) ; extra == 'dev'
Requires-Dist: twine (==3.2.0) ; extra == 'dev'
